{
  "update_time": "2026-07-03 14:46",
  "items": [
    {
      "title": "宏观退潮与产业重塑：铜铝锌在&ldquo;弱现实&rdquo;与&ldquo;强逻辑&rdquo;间的再平衡，今日铜价涨660元/吨",
      "url": "https://www.ccmn.cn/news/ZX003/202607/63258bd829fe4e65806e1d349e078c2e.html",
      "tag": "铜",
      "date": "2026-07-03"
    },
    {
      "title": "● 铜价高位博弈：巨头扩产两难与冶炼端修复的共振",
      "url": "https://www.ccmn.cn/news/ZX003/202607/3809ece9c089463ab02183ebd037cd9b.html",
      "tag": "铜",
      "date": "2026-07-03"
    },
    {
      "title": "● 长江有色： 精废价差收窄利好精铜消费  3日铜价或上涨",
      "url": "https://www.ccmn.cn/news/ZX003/202607/8a050b6f2e264f0fb92e3d24018e8540.html",
      "tag": "铜",
      "date": "2026-07-03"
    },
    {
      "title": "● 长江有色: 国内社库去化+新兴需求韧性封底   3日铝价或上涨",
      "url": "https://www.ccmn.cn/news/ZX003/202607/4e39cd16300b41caa25f65a06ba262f1.html",
      "tag": "铝",
      "date": "2026-07-03"
    },
    {
      "title": "● 长江有色：2日铝价大涨    今日刚需成交乏力",
      "url": "https://www.ccmn.cn/news/ZX003/202607/eee9e646a4884202af27422047aee9a4.html",
      "tag": "铝",
      "date": "2026-07-03"
    },
    {
      "title": "● 长江有色：2日氧化铝期价收跌1.87%   整体成交反馈寡淡",
      "url": "https://www.ccmn.cn/news/ZX003/202607/8235a76b72884eb4a89f90990588ce0b.html",
      "tag": "铝",
      "date": "2026-07-03"
    },
    {
      "title": "稀土行情: 上海有色网稀土氧化物价格专区为用户提供今日最新稀土金属氧化物价格行情,包括氧化镧价格、氧化铈价格、氧化镨价格、氧化钕价格、镨钕氧化物价格、氧化钐价格、氧化铕价格、氧化钆价格、氧化铽价格、氧化镝价格、氧",
      "url": "https://hq.smm.cn/h5/rare-earth-metal-oxides-price",
      "tag": "稀土",
      "date": "2026-07-03"
    },
    {
      "title": "Mysteel日报：国内无取向硅钢市场需求偏弱 成交表现不佳",
      "url": "https://gc.mysteel.com/a/26070217/EDFCB72B81AEFFCE.html",
      "tag": "硅钢",
      "date": "2026-07-03"
    },
    {
      "title": "Mysteel：风电全产业链深度解析——从政策红利到用钢机遇（七）",
      "url": "https://gc.mysteel.com/a/26062610/6F91563469ADA910.html",
      "tag": "硅钢",
      "date": "2026-07-03"
    },
    {
      "title": "Mysteel日报：国内无取向硅钢价格弱稳 成交表现不佳",
      "url": "https://gc.mysteel.com/a/26070117/F6CC35F2164AB2AC.html",
      "tag": "硅钢",
      "date": "2026-07-03"
    }
  ]
}